<?xml version="1.0" encoding="UTF-8"?><CHAT xmlns="http://www.talkbank.org/ns/talkbank" xmlns:xsi="http://www.w3.org/2001/XMLSchema-instance" xsi:schemaLocation="http://www.talkbank.org/ns/talkbank http://talkbank.org/software/talkbank.xsd" Media="KBFRE01G" Mediatypes="audio" PID="KBFRE01G" Version="2.5.0" Lang="eng" Corpus="CABNC" Date="1991-12-04 "><Participants><participant custom-field="SES is C2" id="PS04U" role="Unidentified" sex="female" language="eng" age="P34Y1M1D" name="Brenda" group="housewife"/><participant custom-field="SES is UU" id="PS04Y" role="Unidentified" sex="female" language="eng" age="P62Y1M1D" name="Jean" group="housewife"/></Participants><comment type="Transcriber">LongmanELT</comment><comment type="Location">Avon:  Bristol </comment><comment type="Room Layout">Home</comment><comment type="Situation">Unspecified</comment><comment type="Date">04-DEC-1991</comment><comment type="New Episode"/><u who="PS04Y" uID="u1"><w>Because</w><w>I</w><w>have</w><w>n't</w><w>it</w><w>'s</w><w>y</w><w>you</w><w>'re</w><w>going</w><w>to</w><w>put</w><w>that</w><w>away</w><w>for</w><w>me</w><w>are</w><w>n't</w><w>you</w><w>That</w><w>black</w><w>bag</w>&#xD;
<t type="p"/><postcode>dia</postcode></u><u who="PS04U" uID="u2"><w>Yeah</w><w>put</w><w>it</w><w>in</w><w>that</w><w>bag</w>&#xD;
<t type="p"/><postcode>dia</postcode></u><u who="PS04Y" uID="u3"><w>That</w><w>'s</w><w>a</w><w>good</w><w>idea</w>&#xD;
<t type="p"/><postcode>dia</postcode></u><u who="PS04U" uID="u4"><w>On</w><w>the</w><w>top</w><w>You</w><w>'ve</w><w>got</w><w>your</w><w>other</w><w>bits</w><w>and</w><w>pieces</w><w>in</w><w>there</w><w>Otherwise</w><w>you</w><w>'ll</w><w>forget</w><w>it</w>&#xD;
<t type="p"/><postcode>dia</postcode></u><u who="PS04Y" uID="u5"><w>Well</w><w>I</w><w>wo</w><w>n't</w><w>forget</w><w>it</w><w>tonight</w><w>because</w><w>no</w><w>I</w><w>wo</w><w>n't</w><w>be</w><w>wearing</w><w>it</w><w>will</w><w>I</w><w>here</w><w>I</w><w>shall</w><w>wear</w><w>it</w><w>at</w><w>Marge</w><w>'s</w>&#xD;
<t type="p"/><postcode>dia</postcode></u><u who="PS04U" uID="u6"><w>No</w><w>you</w><w>'re</w><w>at</w><w>Marge</w><w>'s</w>&#xD;
<t type="p"/><postcode>dia</postcode></u><u who="PS04Y" uID="u7"><w>Yes</w>&#xD;
<t type="p"/><postcode>dia</postcode></u><u who="PS04U" uID="u8"><w>Right</w><w>so</w><w>we</w><w>'ll</w><w>take</w><w>the</w><w>voucher</w>&#xD;
<t type="p"/><postcode>dia</postcode></u><u who="PS04Y" uID="u9"><w>I</w><w>like</w><w>that</w><w>outfit</w><w>Brenda</w>&#xD;
<t type="p"/><postcode>dia</postcode></u><u who="PS04U" uID="u10"><w>Yeah</w><w>but</w><w>look</w><w>how</w><w>it</w><w>fitted</w><w>me</w><w>when</w><w>I</w><w>bought</w><w>it</w><w>Look</w><w>at</w><w>it</w>&#xD;
<t type="p"/><postcode>dia</postcode></u><u who="PS04Y" uID="u11"><w>Yeah</w><w>quite</w><w>Yeah</w>&#xD;
<t type="p"/><postcode>dia</postcode></u><u who="PS04U" uID="u12"><w>I</w><w>live</w><w>in</w><w>it</w><w>You</w><w>can</w><w>tell</w><w>by</w><w>the</w><w>trousers</w><w>They</w><w>really</w><w>get</w><w>sort</w><w>of</w>&#xD;
<t type="p"/><postcode>dia</postcode></u><u who="PS04Y" uID="u13"><w>It</w><w>'s</w><w>a</w><w>lovely</w><w>colour</w>&#xD;
<t type="p"/><postcode>dia</postcode></u><u who="PS04U" uID="u14"><w>I</w><w>was</w><w>gon</w><w>na</w><w>say</w><w>look</w><w>at</w><w>the</w><w>socks</w><w>Are</w><w>n't</w><w>they</w><w>dreadful</w>&#xD;
<t type="p"/><postcode>dia</postcode></u><u who="PS04Y" uID="u15"><w>Ah</w><w>no</w>&#xD;
<t type="p"/><postcode>dia</postcode></u><u who="PS04U" uID="u16"><w>Where</w><w>'s</w><w>is</w><w>erm</w><w>where</w><w>'s</w><w>my</w><w>handbag</w><w>No</w><w>It</w><w>'s</w><w>not</w><w>there</w>&#xD;
<t type="p"/><postcode>dia</postcode></u><u who="PS04Y" uID="u17"><w>Here</w><w>it</w><w>is</w><w>Brenda</w>&#xD;
<t type="p"/><postcode>dia</postcode></u><u who="PS04U" uID="u18"><w>No</w><w>it</w><w>'s</w><w>here</w>&#xD;
<t type="p"/><postcode>dia</postcode></u><u who="PS04Y" uID="u19"><w>Oh</w><w>Oh</w><w>I</w><w>thought</w><w>that</w><w>was</w><w>it</w>&#xD;
<t type="p"/><postcode>dia</postcode></u><u who="PS04U" uID="u20"><w>That</w><w>'s</w><w>yours</w>&#xD;
<t type="p"/><postcode>dia</postcode></u><u who="PS04Y" uID="u21"><w>that</w><w>'s</w><w>mine</w><w>yeah</w><w>tee</w><w>hee</w>&#xD;
<t type="p"/><postcode>dia</postcode></u><u who="PS04U" uID="u22"><w>Did</w><w>I</w><w>put</w><w>the</w><w>list</w><w>oh</w><w>yeah</w><w>things</w><w>to</w><w>get</w><w>okay</w><w>Right</w><w>Jean</w><w>presents</w><w>for</w><w>That</w><w>'s</w><w>what</w><w>you</w><w>'ve</w><w>got</w><w>Do</w><w>you</w><w>want</w><w>to</w><w>take</w><w>what</w><w>you</w><w>'ve</w><w>got</w><w>just</w><w>in</w><w>case</w><w>you</w><w>think</w>&#xD;
<t type="p"/><postcode>dia</postcode></u><u who="PS04Y" uID="u23"><w>Mm</w><w>I</w><w>was</w><w>gon</w><w>na</w><w>say</w>&#xD;
<t type="p"/><postcode>dia</postcode></u><u who="PS04U" uID="u24"><w>ooh</w><w>have</w><w>I</w><w>bought</w><w>so</w><w>and</w><w>so</w>&#xD;
<t type="p"/><postcode>dia</postcode></u><u who="PS04Y" uID="u25"><w>Could</w><w>change</w><w>that</w><w>Yeah</w><w>Yeah</w>&#xD;
<t type="p"/><postcode>dia</postcode></u><u who="PS04U" uID="u26"><w>Or</w><w>change</w><w>it</w>&#xD;
<t type="p"/><postcode>dia</postcode></u><u who="PS04Y" uID="u27"><w>Mm</w>&#xD;
<t type="p"/><postcode>dia</postcode></u><u who="PS04U" uID="u28"><w>So</w><w>I</w><w>suppose</w><w>what</w><w>you</w><w>do</w><w>with</w><w>Debs</w><w>is</w><w>er</w><w>tell</w><w>them</w><w>you</w><w>want</w><w>the</w><w>whole</w><w>discount</w><w>and</w><w>I</w><w>suppose</w><w>they</w><w>give</w><w>you</w><w>a</w><w>card</w><w>for</w><w>each</w><w>floor</w><w>cos</w><w>you</w><w>ca</w><w>n't</w><w>walk</w><w>around</w><w>with</w><w>it</w><w>each</w><w>floor</w><w>can</w><w>you</w>&#xD;
<t type="p"/><postcode>dia</postcode></u><u who="PS04Y" uID="u29"><w>No</w><w>I</w><w>er</w><w>we</w><w>we</w><w>'ll</w><w>have</w><w>to</w><w>start</w><w>by</w><w>asking</w><w>as</w><w>you</w><w>say</w><w>Find</w><w>out</w><w>what</w><w>the</w><w>system</w><w>is</w><w>Yes</w>&#xD;
<t type="p"/><postcode>dia</postcode></u><u who="PS04U" uID="u30"><w>If</w><w>you</w><w>get</w><w>like</w><w>you</w><w>did</w><w>at</w><w>John</w><w>Lewis</w><w>you</w><w>get</w><w>a</w><w>card</w>&#xD;
<t type="p"/><postcode>dia</postcode></u><u who="PS04Y" uID="u31"><w>That</w><w>'s</w><w>right</w>&#xD;
<t type="p"/><postcode>dia</postcode></u><u who="PS04U" uID="u32"><w>That</w><w>'d</w><w>be</w><w>better</w>&#xD;
<t type="p"/><postcode>dia</postcode></u><u who="PS04Y" uID="u33"><w>Yes</w>&#xD;
<t type="p"/><postcode>dia</postcode></u><u who="PS04U" uID="u34"><w>We</w><w>could</w><w>then</w><w>leave</w><w>it</w><w>and</w><w>say</w><w>we</w><w>'ll</w><w>pick</w><w>it</w><w>up</w><w>in</w><w>an</w><w>hour</w><w>or</w><w>so</w>&#xD;
<t type="p"/><postcode>dia</postcode></u><u who="PS04Y" uID="u35"><w>Yes</w><w>Yes</w>&#xD;
<t type="p"/><postcode>dia</postcode></u><u who="PS04U" uID="u36"><w>then</w><w>go</w><w>and</w><w>do</w><w>Marks</w><w>and</w><w>Smiths</w>&#xD;
<t type="p"/><postcode>dia</postcode></u><u who="PS04Y" uID="u37"><w>Yes</w>&#xD;
<t type="p"/><postcode>dia</postcode></u><u who="PS04U" uID="u38"><w>and</w><w>drive</w><w>the</w><w>car</w><w>round</w>&#xD;
<t type="p"/><postcode>dia</postcode></u><u who="PS04Y" uID="u39"><w>Mm</w><w>Mm</w><w>Mm</w><w>Good</w><w>idea</w>&#xD;
<t type="p"/><postcode>dia</postcode></u><u who="PS04U" uID="u40"><w>Brekkypoos</w><w>still</w><w>got</w><w>ten</w><w>more</w><w>I</w><w>'ll</w><w>have</w><w>to</w><w>be</w><w>careful</w><w>this</w><w>does</w><w>n't</w><w>oh</w><w>it</w><w>'s</w><w>hot</w><w>in</w><w>here</w><w>Jean</w><w>is</w><w>n't</w><w>it</w>&#xD;
<t type="p"/><postcode>dia</postcode></u><u who="PS04Y" uID="u41"><w>Yes</w><w>is</w><w>n't</w><w>it</w>&#xD;
<t type="p"/><postcode>dia</postcode></u><u who="PS04U" uID="u42"><w>What</w><w>'s</w><w>this</w><w>one</w>&#xD;
<t type="p"/><postcode>dia</postcode></u><u who="PS04Y" uID="u43"><w>That</w><w>'s</w><w>er</w><w>that</w><w>'s</w>&#xD;
<t type="p"/><postcode>dia</postcode></u><u who="PS04U" uID="u44"><w>Mind</w><w>you</w><w>I</w><w>do</w><w>n't</w><w>want</w><w>that</w><w>too</w><w>awkward</w>&#xD;
<t type="p"/><postcode>dia</postcode></u><u who="PS04Y" uID="u45"><w>What</w><w>did</w><w>I</w><w>do</w><w>with</w><w>my</w><w>glasses</w><w>Brenda</w><w>I</w><w>had</w><w>them</w><w>in</w><w>my</w><w>hand</w><w>a</w><w>moment</w><w>ago</w><w>Oh</w><w>there</w><w>they</w><w>are</w>&#xD;
<t type="p"/><postcode>dia</postcode></u><u who="PS04U" uID="u46"><w>Oh</w><w>look</w><w>at</w><w>the</w><w>marks</w><w>on</w><w>this</w><w>carpet</w><w>Atrocious</w><w>We</w><w>'re</w><w>pulling</w><w>this</w><w>carpet</w><w>up</w><w>after</w><w>Christmas</w>&#xD;
<t type="p"/><postcode>dia</postcode></u><u who="PS04Y" uID="u47"><w>Aha</w>&#xD;
<t type="p"/><postcode>dia</postcode></u><u who="PS04U" uID="u48"><w>We</w><w>'re</w><w>going</w><w>back</w><w>to</w><w>the</w><w>woodblock</w><w>flooring</w>&#xD;
<t type="p"/><postcode>dia</postcode></u><u who="PS04Y" uID="u49"><w>How</w><w>nice</w><w>Oh</w><w>I</w><w>love</w><w>it</w><w>Brenda</w>&#xD;
<t type="p"/><postcode>dia</postcode></u><u who="PS04U" uID="u50"><w>Well</w><w>I</w><w>mean</w><w>we</w><w>'ve</w><w>those</w><w>biscuits</w><w>are</w><w>stale</w><w>now</w><w>see</w><w>You</w><w>know</w><w>the</w><w>biscuit</w><w>tin</w>&#xD;
<t type="p"/><postcode>dia</postcode></u><u who="PS04Y" uID="u51"><w>Mm</w><w>Mm</w><w>Yeah</w><w>Quite</w>&#xD;
<t type="p"/><postcode>dia</postcode></u><u who="PS04U" uID="u52"><w>You</w><w>end</w><w>up</w><w>throwing</w><w>them</w><w>out</w>&#xD;
<t type="p"/><postcode>dia</postcode></u><u who="PS04Y" uID="u53"><w>I</w><w>do</w><w>n't</w><w>like</w><w>to</w><w>throw</w><w>them</w><w>away</w><w>without</w><w>asking</w><w>you</w>&#xD;
<t type="p"/><postcode>dia</postcode></u><u who="PS04U" uID="u54"><w>No</w><w>But</w><w>I</w><w>I</w><w>would</w><w>n't</w><w>leave</w><w>them</w>&#xD;
<t type="p"/><postcode>dia</postcode></u><u who="PS04Y" uID="u55"><w>No</w><w>I</w><w>'m</w><w>going</w><w>to</w><w>have</w><w>a</w><w>little</w><w>quick</w><w>look</w><w>at</w><w>Ikea</w><w>Oh</w><w>oh</w>&#xD;
<t type="p"/><postcode>dia</postcode></u><u who="PS04U" uID="u56"><w>Course</w><w>you</w><w>can</w><w>The</w><w>decorator</w><w>that</w><w>are</w><w>in</w><w>at</w><w>Peter</w><w>'s</w><w>at</w><w>the</w><w>moment</w><w>erm</w><w>they</w><w>do</w><w>everything</w><w>They</w><w>'re</w><w>fantastic</w><w>And</w><w>he</w><w>was</w><w>saying</w><w>he</w><w>said</w><w>oh</w><w>you</w><w>'ve</w><w>been</w><w>good</w><w>you</w><w>'ve</w><w>been</w><w>feeding</w><w>us</w><w>with</w><w>cups</w><w>of</w><w>teas</w><w>They</w><w>charge</w><w>seventy</w><w>pound</w><w>a</w><w>day</w><w>per</w><w>person</w><w>and</w><w>he</w><w>said</w><w>oh</w><w>we</w><w>'ll</w><w>charge</w><w>you</w><w>next</w><w>to</w><w>nothing</w><w>He</w><w>said</w><w>in</w><w>fact</w><w>we</w><w>'ll</w><w>come</w><w>down</w><w>and</w><w>he</w><w>said</w><w>cos</w><w>the</w><w>er</w><w>it</w><w>'s</w><w>cracked</w><w>round</w><w>the</w><w>outside</w><w>He</w><w>said</w><w>and</w><w>we</w><w>'ll</w><w>take</w><w>it</w><w>up</w><w>and</w><w>repair</w><w>it</w><w>for</w><w>you</w><w>He</w><w>said</w><w>we</w><w>might</w><w>sort</w><w>of</w><w>say</w><w>to</w><w>you</w><w>right</w><w>we</w><w>want</w><w>fifty</w><w>quid</w>&#xD;
<t type="p"/><postcode>dia</postcode></u><u who="PS04Y" uID="u57"><w>Mm</w><w>Mm</w>&#xD;
<t type="p"/><postcode>dia</postcode></u><u who="PS04U" uID="u58"><w>But</w><w>he</w><w>said</w><w>we</w><w>wo</w><w>n't</w><w>charge</w><w>you</w><w>the</w><w>daily</w><w>rate</w><w>we</w><w>'ll</w><w>just</w><w>charge</w><w>you</w><w>for</w><w>the</w><w>job</w>&#xD;
<t type="p"/><postcode>dia</postcode></u><u who="PS04Y" uID="u59"><w>No</w><w>No</w><w>No</w><w>Yeah</w><w>Lovely</w>&#xD;
<t type="p"/><postcode>dia</postcode></u><u who="PS04U" uID="u60"><w>And</w><w>he</w><w>said</w><w>if</w><w>it</w><w>'s</w><w>that</w><w>bad</w><w>we</w><w>'ll</w><w>strip</w><w>it</w><w>for</w><w>you</w>&#xD;
<t type="p"/><postcode>dia</postcode></u><u who="PS04Y" uID="u61"><w>Oh</w><w>good</w>&#xD;
<t type="p"/><postcode>dia</postcode></u><u who="PS04U" uID="u62"><w>And</w><w>re-</w><w>sort</w><w>of</w><w>d</w><w>do</w><w>it</w>&#xD;
<t type="p"/><postcode>dia</postcode></u><u who="PS04Y" uID="u63"><w>Re-</w><w>re-sand</w><w>yeah</w><w>You</w><w>'ll</w><w>love</w><w>it</w><w>You</w><w>'ll</w><w>love</w><w>it</w>&#xD;
<t type="p"/><postcode>dia</postcode></u><u who="PS04U" uID="u64"><w>Well</w><w>it</w><w>'s</w><w>all</w><w>in</w><w>the</w><w>hall</w><w>and</w><w>Dave</w><w>said</w><w>the</w><w>kids</w><w>are</w><w>older</w><w>now</w><w>We</w><w>'re</w><w>fed</w><w>up</w><w>with</w><w>carpets</w><w>and</w><w>stain</w>&#xD;
<t type="p"/><postcode>dia</postcode></u><u who="PS04Y" uID="u65"><w>Yes</w><w>Yes</w>&#xD;
<t type="p"/><postcode>dia</postcode></u><u who="PS04U" uID="u66"><w>I</w><w>mean</w><w>this</w><w>carpet</w><w>'s</w><w>three</w><w>years</w><w>old</w><w>I</w><w>mean</w><w>it</w><w>'s</w>&#xD;
<t type="p"/><postcode>dia</postcode></u><u who="PS04Y" uID="u67"><w>I</w><w>know</w><w>I</w><w>know</w>&#xD;
<t type="p"/><postcode>dia</postcode></u><u who="PS04U" uID="u68"><w>it</w><w>'s</w><w>even</w><w>going</w><w>here</w><w>now</w>&#xD;
<t type="p"/><postcode>dia</postcode></u><u who="PS04Y" uID="u69"><w>Mm</w>&#xD;
<t type="p"/><postcode>dia</postcode></u><u who="PS04U" uID="u70"><w>And</w><w>you</w><w>keep</w><w>washing</w><w>it</w>&#xD;
<t type="p"/><postcode>dia</postcode></u><u who="PS04Y" uID="u71"><w>Yeah</w><w>Oh</w>&#xD;
<t type="p"/><postcode>dia</postcode></u><u who="PS04U" uID="u72"><w>And</w><w>it</w><w>just</w><w>does</w><w>n't</w><w>does</w><w>it</w>&#xD;
<t type="p"/><postcode>dia</postcode></u><u who="PS04Y" uID="u73"><w>No</w>&#xD;
<t type="p"/><postcode>dia</postcode></u><u who="PS04U" uID="u74"><w>Does</w><w>nothing</w><w>happens</w>&#xD;
<t type="p"/><postcode>dia</postcode></u><u who="PS04Y" uID="u75"><w>Yeah</w>&#xD;
<t type="p"/><postcode>dia</postcode></u><u who="PS04U" uID="u76"><w>So</w><w>two</w><w>there</w><w>I</w><w>give</w><w>you</w><w>your</w><w>lipstick</w><w>did</w><w>n't</w><w>I</w>&#xD;
<t type="p"/><postcode>dia</postcode></u><u who="PS04Y" uID="u77"><w>Mm</w><w>Yeah</w>&#xD;
<t type="p"/><postcode>dia</postcode></u><u who="PS04U" uID="u78"><w>Why</w><w>have</w><w>we</w><w>got</w><w>so</w><w>many</w><w>cushions</w><w>I</w><w>said</w><w>well</w><w>do</w><w>n't</w><w>worry</w><w>we</w><w>'re</w><w>gon</w><w>na</w><w>have</w><w>more</w>&#xD;
<t type="p"/><postcode>dia</postcode></u><u who="PS04Y" uID="u79"><e><action/></e><t type="p"/><postcode>dia</postcode></u><u who="PS04U" uID="u80"><w>I</w><w>said</w><w>they</w><w>even</w><w>fight</w><w>then</w><w>there</w><w>'s</w><w>not</w><w>enough</w>&#xD;
<t type="p"/><postcode>dia</postcode></u><u who="PS04Y" uID="u81"><w>Yeah</w><w>I</w><w>know</w><w>Ah</w><w>I</w><w>wish</w><w>I</w><w>could</w><w>lift</w><w>my</w><w>carpet</w><w>up</w><w>I</w><w>hate</w><w>it</w><w>But</w><w>I</w><w>must</w><w>say</w><w>the</w><w>carpet</w><w>looks</w><w>better</w><w>in</w><w>the</w><w>sitting</w><w>room</w><w>since</w>&#xD;
<t type="p"/><postcode>dia</postcode></u><u who="PS04U" uID="u82"><w>Look</w><w>at</w><w>this</w><w>lovely</w><w>stuff</w><w>Dave</w><w>does</w><w>n't</w><w>like</w><w>it</w>&#xD;
<t type="p"/><postcode>dia</postcode></u><u who="PS04Y" uID="u83"><w>we</w><w>took</w><w>the</w><w>colour</w><w>down</w>&#xD;
<t type="p"/><postcode>dia</postcode></u><u who="PS04U" uID="u84"><w>but</w><w>I</w><w>love</w><w>it</w><w>That</w><w>'s</w><w>a</w><w>normal</w><w>skirting</w>&#xD;
<t type="p"/><postcode>dia</postcode></u><u who="PS04Y" uID="u85"><w>Mm</w>&#xD;
<t type="p"/><postcode>dia</postcode></u><u who="PS04U" uID="u86"><w>This</w><w>is</w><w>what</w><w>the</w><w>decorators</w>&#xD;
<t type="p"/><postcode>dia</postcode></u><u who="PS04Y" uID="u87"><w>Oh</w><w>yes</w><w>That</w><w>'s</w><w>what</w><w>I</w><w>'ve</w><w>got</w>&#xD;
<t type="p"/><postcode>dia</postcode></u><u who="PS04U" uID="u88"><w>Yeah</w><w>it</w><w>'s</w><w>lovely</w>&#xD;
<t type="p"/><postcode>dia</postcode></u><u who="PS04Y" uID="u89"><w>Yes</w>&#xD;
<t type="p"/><postcode>dia</postcode></u><u who="PS04U" uID="u90"><w>But</w><w>Dave</w><w>do</w><w>n't</w><w>like</w><w>it</w><w>and</w><w>he</w><w>said</w><w>the</w><w>room</w><w>'s</w><w>too</w><w>small</w><w>And</w><w>Peter</w><w>'s</w><w>had</w><w>that</w><w>and</w><w>he</w><w>'s</w><w>had</w><w>dado</w><w>and</w><w>the</w><w>dado</w><w>bars</w>&#xD;
<t type="p"/><postcode>dia</postcode></u><u who="PS04Y" uID="u91"><w>Ah</w>&#xD;
<t type="p"/><postcode>dia</postcode></u><u who="PS04U" uID="u92"><w>They</w><w>look</w><w>so</w><w>nice</w>&#xD;
<t type="p"/><postcode>dia</postcode></u><u who="PS04Y" uID="u93"><w>What</w><w>a</w><w>lot</w><w>of</w><w>people</w><w>are</w><w>doing</w><w>is</w><w>they</w><w>'re</w><w>not</w><w>putting</w><w>up</w><w>rails</w><w>but</w><w>they</w><w>'re</w><w>putting</w><w>up</w><w>a</w><w>erm</w><w>a</w><w>border</w><w>halfway</w><w>up</w><w>are</w><w>n't</w><w>they</w><w>or</w><w>just</w><w>not</w><w>quite</w><w>halfway</w><w>up</w><w>the</w><w>wall</w><w>Have</w><w>you</w><w>seen</w><w>that</w>&#xD;
<t type="p"/><postcode>dia</postcode></u><u who="PS04U" uID="u94"><w>Yeah</w>&#xD;
<t type="p"/><postcode>dia</postcode></u><u who="PS04Y" uID="u95"><w>And</w><w>perhaps</w><w>with</w><w>a</w><w>different</w><w>wallpaper</w><w>below</w><w>and</w><w>above</w>&#xD;
<t type="p"/><postcode>dia</postcode></u><u who="PS04U" uID="u96"><w>Below</w><w>and</w><w>above</w><w>That</w><w>'s</w><w>right</w>&#xD;
<t type="p"/><postcode>dia</postcode></u><u who="PS04Y" uID="u97"><w>Yes</w>&#xD;
<t type="p"/><postcode>dia</postcode></u><u who="PS04U" uID="u98"><w>Right</w><w>Let's</w><w>just</w><w>sort</w><w>this</w><w>out</w>&#xD;
<t type="p"/><postcode>dia</postcode></u></CHAT>