<?xml version="1.0" encoding="UTF-8"?><CHAT xmlns="http://www.talkbank.org/ns/talkbank" xmlns:xsi="http://www.w3.org/2001/XMLSchema-instance" xsi:schemaLocation="http://www.talkbank.org/ns/talkbank http://talkbank.org/software/talkbank.xsd" Media="021A-C0897X0023XX-ABZZPO" Mediatypes="audio" PID="KBKRE02P" Version="2.5.0" Lang="eng" Corpus="CABNC" Date="1991-06-01 "><Participants><participant custom-field="SES is AB" id="PS05X" role="Unidentified" sex="male" language="eng" age="P51Y1M1D" name="Chris" group="export merchant"/><participant custom-field="SES is AB" id="PS101" role="Unidentified" sex="female" language="eng" age="P54Y1M1D" name="Norrine" group="teacher"/></Participants><comment type="Transcriber">LongmanELT</comment><comment type="Location">London:  Bromley </comment><comment type="Room Layout">Home</comment><comment type="Situation">Unspecified</comment><comment type="Date">01-JUN-1991</comment><comment type="New Episode"/><u who="PS101" uID="u1"><w>Oh</w><w>you</w><w>had</w><w>a</w><w>good</w><w>day</w><w>today</w>&#xD;
<t type="p"/><postcode>dia</postcode><media start="1172.70250" end="1173.70251" unit="s"/></u><u who="PS05X" uID="u2"><e><action/></e><t type="p"/><postcode>dia</postcode></u><u who="PS101" uID="u3"><w>Mm</w>&#xD;
<t type="p"/><postcode>dia</postcode><media start="1173.70250" end="1173.77251" unit="s"/></u><u who="PS05X" uID="u4"><w>bring</w><w>a</w><w>I</w><w>knew</w><w>there</w><w>was</w><w>something</w><w>else</w><w>I</w><w>had</w><w>to</w><w>bring</w><w>fabric</w>&#xD;
<t type="p"/><postcode>dia</postcode><media start="1174.07250" end="1189.08251" unit="s"/></u><u who="PS101" uID="u5"><w>Did</w><w>you</w><w>get</w><w>the</w><w>library</w><w>books</w><w>back</w>&#xD;
<t type="p"/><postcode>dia</postcode><media start="1193.19250" end="1194.35251" unit="s"/></u><u who="PS05X" uID="u6"><w>Not</w><w>really</w><w>warm</w><w>is</w><w>it</w>&#xD;
<t type="p"/><postcode>dia</postcode><media start="1194.53250" end="1199.58251" unit="s"/></u><u who="PS101" uID="u7"><w>It</w><w>is</w><w>n't</w><w>warm</w><w>at</w><w>all</w>&#xD;
<t type="p"/><postcode>dia</postcode><media start="1200.76250" end="1202.40251" unit="s"/></u></CHAT>